jupyterhub_crowd/__init__.py
jupyterhub_crowd/auth.py
jupyterhub_crowd-0.0.2.dist-info/LICENSE
jupyterhub_crowd-0.0.2.dist-info/METADATA
jupyterhub_crowd-0.0.2.dist-info/WHEEL
jupyterhub_crowd-0.0.2.dist-info/top_level.txt
jupyterhub_crowd-0.0.2.dist-info/RECORD
