Metadata-Version: 2.1
Name: jupyterhub-crowd
Version: 0.0.2
Summary: Crowd authenticator for JupyterHub
Home-page: https://github.com/hkjinlee/jupyterhub_crowd
Author: Jin, Heonkyu
Author-email: heonkyu.jin@gmail.com
License: UNKNOWN
Platform: UNKNOWN
Classifier: Programming Language :: Python :: 3
Classifier: License :: OSI Approved :: MIT License
Classifier: Operating System :: OS Independent
Requires-Dist: jupyterhub
Requires-Dist: Crowd
